{
  "type_description_msg": {
    "type_description": {
      "type_name": "ublox_msgs/msg/NavSTATUS",
      "fields": [
        {
          "name": "i_tow",
          "type": {
            "type_id": 7,
            "capacity": 0,
            "string_capacity": 0,
            "nested_type_name": ""
          },
          "default_value": ""
        },
        {
          "name": "gps_fix",
          "type": {
            "type_id": 3,
            "capacity": 0,
            "string_capacity": 0,
            "nested_type_name": ""
          },
          "default_value": ""
        },
        {
          "name": "flags",
          "type": {
            "type_id": 3,
            "capacity": 0,
            "string_capacity": 0,
            "nested_type_name": ""
          },
          "default_value": ""
        },
        {
          "name": "fix_stat",
          "type": {
            "type_id": 3,
            "capacity": 0,
            "string_capacity": 0,
            "nested_type_name": ""
          },
          "default_value": ""
        },
        {
          "name": "flags2",
          "type": {
            "type_id": 3,
            "capacity": 0,
            "string_capacity": 0,
            "nested_type_name": ""
          },
          "default_value": ""
        },
        {
          "name": "ttff",
          "type": {
            "type_id": 7,
            "capacity": 0,
            "string_capacity": 0,
            "nested_type_name": ""
          },
          "default_value": ""
        },
        {
          "name": "msss",
          "type": {
            "type_id": 7,
            "capacity": 0,
            "string_capacity": 0,
            "nested_type_name": ""
          },
          "default_value": ""
        }
      ]
    },
    "referenced_type_descriptions": []
  },
  "type_hashes": [
    {
      "type_name": "ublox_msgs/msg/NavSTATUS",
      "hash_string": "RIHS01_4a5b17f3ef442656eb431a3df54bc44ca642c4b5a1254462f89bd895171522d4"
    }
  ]
}